geothai/__init__.py
geothai/data/__init__.py
geothai/services/__init__.py
geothai/services/district_service.py
geothai/services/postal_code_service.py
geothai/services/province_service.py
geothai/services/subdistrict_service.py
geothai/types/__init__.py
geothai/types/district_type.py
geothai/types/metadata_type.py
geothai/types/postal_code_type.py
geothai/types/province_type.py
geothai/types/subdistrict_type.py
geothai/utils/__init__.py
geothai/utils/criteria_matcher.py
geothai-2.0.0.dist-info/licenses/LICENSE
geothai-2.0.0.dist-info/METADATA
geothai-2.0.0.dist-info/WHEEL
geothai-2.0.0.dist-info/top_level.txt
geothai-2.0.0.dist-info/RECORD
