Metadata-Version: 2.4
Name: geothai
Version: 2.0.0
Summary: An python package that allows to access detailed geographic data on Thailand, including provinces, districts, subdistricts and postal codes. 🌟
Author-email: GeoThai Team <contact@fasu.dev>
License: MIT License
Project-URL: Homepage, https://github.com/GeoThai/python-library
Classifier: Programming Language :: Python :: 3
Classifier: License :: OSI Approved :: MIT License
Classifier: Operating System :: OS Independent
Requires-Python: >=3.9
License-File: LICENSE
Dynamic: license-file
